pycrostates/__init__.py
pycrostates/__init__.pyi
pycrostates/_typing.py
pycrostates/_typing.pyi
pycrostates/_version.py
pycrostates/cluster/__init__.py
pycrostates/cluster/__init__.pyi
pycrostates/cluster/_base.py
pycrostates/cluster/_base.pyi
pycrostates/cluster/aahc.py
pycrostates/cluster/aahc.pyi
pycrostates/cluster/kmeans.py
pycrostates/cluster/kmeans.pyi
pycrostates/cluster/utils/__init__.py
pycrostates/cluster/utils/__init__.pyi
pycrostates/cluster/utils/utils.py
pycrostates/cluster/utils/utils.pyi
pycrostates/commands/__init__.py
pycrostates/commands/sys_info.py
pycrostates/datasets/__init__.py
pycrostates/datasets/__init__.pyi
pycrostates/datasets/lemon/__init__.py
pycrostates/datasets/lemon/__init__.pyi
pycrostates/datasets/lemon/lemon.py
pycrostates/datasets/lemon/lemon.pyi
pycrostates/datasets/lemon/data/PREPROCESSED_LEMON_registry.txt
pycrostates/html_templates/__init__.py
pycrostates/html_templates/_templates.py
pycrostates/html_templates/repr/AAHCluster.html.jinja
pycrostates/html_templates/repr/BaseCluster.html.jinja
pycrostates/html_templates/repr/BaseSegmentation.html.jinja
pycrostates/html_templates/repr/ChData.html.jinja
pycrostates/html_templates/repr/ModKMeans.html.jinja
pycrostates/io/__init__.py
pycrostates/io/__init__.pyi
pycrostates/io/ch_data.py
pycrostates/io/ch_data.pyi
pycrostates/io/fiff.py
pycrostates/io/fiff.pyi
pycrostates/io/meas_info.py
pycrostates/io/meas_info.pyi
pycrostates/io/reader.py
pycrostates/io/reader.pyi
pycrostates/metrics/__init__.py
pycrostates/metrics/__init__.pyi
pycrostates/metrics/calinski_harabasz.py
pycrostates/metrics/calinski_harabasz.pyi
pycrostates/metrics/davies_bouldin.py
pycrostates/metrics/davies_bouldin.pyi
pycrostates/metrics/dunn.py
pycrostates/metrics/dunn.pyi
pycrostates/metrics/silhouette.py
pycrostates/metrics/silhouette.pyi
pycrostates/preprocessing/__init__.py
pycrostates/preprocessing/__init__.pyi
pycrostates/preprocessing/extract_gfp_peaks.py
pycrostates/preprocessing/extract_gfp_peaks.pyi
pycrostates-0.6.1.dist-info/LICENSE
pycrostates-0.6.1.dist-info/METADATA
pycrostates-0.6.1.dist-info/WHEEL
pycrostates-0.6.1.dist-info/entry_points.txt
pycrostates-0.6.1.dist-info/top_level.txt
pycrostates-0.6.1.dist-info/RECORD
