Metadata-Version: 2.1
Name: pycrostates
Version: 0.6.1
Summary: A simple open source Python package for EEG microstate segmentation.
Author-email: Victor Férat <victor.ferat@unige.ch>
Maintainer-email: Mathieu Scheltienne <mathieu.scheltienne@fcbg.ch>, Victor Férat <victor.ferat@unige.ch>
License: BSD 3-Clause License
Project-URL: documentation, https://pycrostates.readthedocs.io
Project-URL: homepage, https://pycrostates.readthedocs.io
Project-URL: source, https://github.com/vferat/pycrostates
Project-URL: tracker, https://github.com/vferat/pycrostates/issues
Keywords: brain,eeg,microstates,neuroimaging,neuroscience,python
Classifier: Intended Audience :: Developers
Classifier: Intended Audience :: Science/Research
Classifier: License :: OSI Approved :: BSD License
Classifier: Natural Language :: English
Classifier: Operating System :: MacOS
Classifier: Operating System :: Microsoft :: Windows
Classifier: Operating System :: Unix
Classifier: Programming Language :: Python :: 3 :: Only
Classifier: Programming Language :: Python :: 3.10
Classifier: Programming Language :: Python :: 3.11
Classifier: Programming Language :: Python :: 3.12
Classifier: Programming Language :: Python :: 3.9
Classifier: Topic :: Scientific/Engineering
Requires-Python: >=3.9
License-File: LICENSE
Requires-Dist: decorator
Requires-Dist: jinja2
Requires-Dist: joblib
Requires-Dist: matplotlib >=3.5
Requires-Dist: mne >=1.2
Requires-Dist: numpy >=1.21
Requires-Dist: packaging
Requires-Dist: pooch
Requires-Dist: psutil
Requires-Dist: scikit-learn
Requires-Dist: scipy
Provides-Extra: all
Requires-Dist: pycrostates[build] ; extra == 'all'
Requires-Dist: pycrostates[docs] ; extra == 'all'
Requires-Dist: pycrostates[style] ; extra == 'all'
Requires-Dist: pycrostates[test] ; extra == 'all'
Provides-Extra: build
Requires-Dist: build ; extra == 'build'
Requires-Dist: twine ; extra == 'build'
Provides-Extra: docs
Requires-Dist: intersphinx-registry ; extra == 'docs'
Requires-Dist: memory-profiler ; extra == 'docs'
Requires-Dist: numpydoc ; extra == 'docs'
Requires-Dist: pandas ; extra == 'docs'
Requires-Dist: pydata-sphinx-theme ; extra == 'docs'
Requires-Dist: pymatreader ; extra == 'docs'
Requires-Dist: seaborn ; extra == 'docs'
Requires-Dist: sphinx ; extra == 'docs'
Requires-Dist: sphinx-copybutton ; extra == 'docs'
Requires-Dist: sphinx-design ; extra == 'docs'
Requires-Dist: sphinx-issues ; extra == 'docs'
Requires-Dist: sphinx-gallery ; extra == 'docs'
Requires-Dist: sphinxcontrib-bibtex ; extra == 'docs'
Provides-Extra: stubs
Requires-Dist: isort ; extra == 'stubs'
Requires-Dist: mypy ; extra == 'stubs'
Requires-Dist: ruff >=0.1.8 ; extra == 'stubs'
Provides-Extra: style
Requires-Dist: bibclean ; extra == 'style'
Requires-Dist: codespell[toml] >=2.2.4 ; extra == 'style'
Requires-Dist: isort ; extra == 'style'
Requires-Dist: pydocstyle[toml] ; extra == 'style'
Requires-Dist: ruff >=0.1.8 ; extra == 'style'
Requires-Dist: toml-sort ; extra == 'style'
Requires-Dist: yamllint ; extra == 'style'
Provides-Extra: test
Requires-Dist: pymatreader ; extra == 'test'
Requires-Dist: pytest-cov ; extra == 'test'
Requires-Dist: pytest >=8.0 ; extra == 'test'
